Workbook

Sheet Summary
A1: Invensoft ERP-XBS-Automation Tracker
A2: S.no. | B2: Modules | C2: Total | D2: Completed | E2: In Progress | F2: Pending | G2: % Completed
A3: 1 | B3: PURCHASE - Basic flow for direct GRN withShipping Instruction.Purchase Contract - Create -> Purchase Contract - Review -> Shipping Instruction - Create -> Shipping Instruction - Review -> Goods Receipt Note - Create | C3: 6 | D3: 2 | E3: 1 | F3: 3 | G3: =IF(C3=0,0,D3/C3) -> 0.33333333
A4: 2 | B4: PURCHASE - LOCAL FLAT PRICE - Basic flow for direct GRN without Shipping Instruction Purchase Contract - Create -> Purchase Contract - Review -> Goods Receipt Note - Create | C4: 6 | D4: =COUNTIF(Scenarios!$B$2:$B$500,C4) -> 0 | E4: =COUNTIF(Scenarios!$B$2:$B$500,D4) -> 0 | F4: 6 | G4: =IF(C4=0,0,D4/C4) -> 0
A5: 3 | B5: TICKETING PURCHASE - User has recorded the ticket details and allocated the Flat price purchase contract to the ticket. Purchase Contract - Create -> Purchase Contract - Approval -> Ticket Create -> Ticket Review -> Ticket 1st Weight -> Warehouse Intake/Dispatch -> Ticket 2nd Weight -> Ticket Purchase Allocation. | C5: 6 | D5: =COUNTIF(Scenarios!$B$2:$B$500,C5) -> 0 | E5: =COUNTIF(Scenarios!$B$2:$B$500,D5) -> 0 | F5: 6 | G5: =IF(C5=0,0,D5/C5) -> 0
A6: 4 | B6: SALES - Basic flow for direct DC withShipping Instruction Sales Contract - Create -> Sales Contract - Review -> Shipping Instruction - Create -> Shipping Instruction - Review -> Goods Dispatch Note - Create | C6: 6 | D6: =COUNTIF(Scenarios!$B$2:$B$500,C6) -> 0 | E6: =COUNTIF(Scenarios!$B$2:$B$500,D6) -> 0 | F6: 6 | G6: =IF(C6=0,0,D6/C6) -> 0
A7: 5 | B7: SALES - LOCAL FLAT PRICE - Basic flow for direct DC without Shipping Instruction Sales Contract - Create -> Sales Contract - Review -> Goods Dispatch Note - Create | C7: 6 | D7: =COUNTIF(Scenarios!$B$2:$B$500,C7) -> 0 | E7: =COUNTIF(Scenarios!$B$2:$B$500,D7) -> 0 | F7: 6 | G7: =IF(C7=0,0,D7/C7) -> 0
A8: 6 | B8: TICKETING SALES - User has recorded the ticket details and allocated the Flat price sales contract to the ticket. Sales Contract - Create -> Sales Contract - Approval -> Ticket Create -> Ticket Review -> Ticket 1st Weight -> Warehouse Intake/Dispatch -> Ticket 2nd Weight -> Ticket Sales Allocation. | C8: 6 | D8: =COUNTIF(Scenarios!$B$2:$B$500,C8) -> 0 | E8: =COUNTIF(Scenarios!$B$2:$B$500,D8) -> 0 | F8: 6 | G8: =IF(C8=0,0,D8/C8) -> 0
B9: Total | C9: 40 | D9: 2 | E9: 1 | F9: 6 | G9: =IF(C9=0,0,D9/C9) -> 0.05
A10: S.no. | B10: Overall | C10: Count | D10: Execution Result | E10: Count | F10: Open work by Priority | G10: In Progress | H10: Pending | I10: Total Open
A11: 1 | B11: Total scenarios | C11: =COUNTA(Scenarios!$A$2:$A$500) -> 110 | D11: Pass | E11: 4 | F11: High | G11: =COUNTIFS(Scenarios!$F$2:$F$500,$F11,Scenarios!$E$2:$E$500,"In Progress") -> 0 | H11: =COUNTIFS(Scenarios!$F$2:$F$500,$F11,Scenarios!$E$2:$E$500,"Pending") -> 14 | I11: =G11+H11 -> 14
A12: 2 | B12: Completed | C12: =COUNTIF(Scenarios!$E$2:$E$500,"Completed") -> 78 | D12: Fail | E12: =COUNTIF(Scenarios!$H$2:$H$500,D12) -> 0 | F12: Medium | G12: =COUNTIFS(Scenarios!$F$2:$F$500,$F12,Scenarios!$E$2:$E$500,"In Progress") -> 1 | H12: =COUNTIFS(Scenarios!$F$2:$F$500,$F12,Scenarios!$E$2:$E$500,"Pending") -> 13 | I12: =G12+H12 -> 14
A13: 3 | B13: In Progress | C13: =COUNTIF(Scenarios!$E$2:$E$500,"In Progress") -> 1 | D13: Skipped | E13: =COUNTIF(Scenarios!$H$2:$H$500,D13) -> 0 | F13: Low | G13: =COUNTIFS(Scenarios!$F$2:$F$500,$F13,Scenarios!$E$2:$E$500,"In Progress") -> 0 | H13: =COUNTIFS(Scenarios!$F$2:$F$500,$F13,Scenarios!$E$2:$E$500,"Pending") -> 1 | I13: =G13+H13 -> 1
A14: 4 | B14: Pending | C14: =COUNTIF(Scenarios!$E$2:$E$500,"Pending") -> 28 | D14: Not Run | E14: 1
A15: 5 | B15: Blocked | C15: 2
A16: 6 | B16: % Completed | C16: =IF(C11=0,0,C12/C11) -> 0.70909091
A17: 7 | B17: Proposed in 'To Add' sheet | C17: =COUNTA('To Add'!$A$2:$A$197) -> 28

Sheet Purchase-flow
A1: Purchase Order Flow
A2: PUR-GRN-SI-001
A3: Step | B3: Module | C3: Action/Test Data | D3: Expected Result | E3: Autoamation Scripts
A4: 1 | B4: Purchase Contract - Create | C4: COFFEE-PURCHASE LOCAL FLAT PRICE @200 INR/Kg, Vendor 1, Robusta Cherry RC RAW 20 MT | D4: Contract created successfully | E4: Completed
A5: 2 | B5: Verification | C5: Dashboard & Commodity Contract Report | D5: Details displayed correctly | E5: Completed
A6: 3 | B6: Contract Review | C6: Approve contract | D6: Contract approved | E6: Completed
A7: 4 | B7: Verification | C7: Dashboard & Report | D7: Details updated correctly
A8: 5 | B8: Shipping Instruction Create | C8: RC RAW 10 MT | D8: SI created successfully
A9: 6 | B9: SI Review | C9: Approve SI | D9: SI approved
A10: 7 | B10: GRN Create | C10: RC RAW 10 MT | D10: GRN created successfully
A11: 8 | B11: Verification | C11: Dashboard, Commodity Contract Report, GRN Summary | D11: Data reflected correctly
A12: PUR-GRN-NO-SI-001
A13: Step | B13: Module | C13: Action/Test Data | D13: Expected Result | E13: Autoamation Scripts
A14: 1 | B14: Purchase Contract - Create | C14: COFFEE-PURCHASE LOCAL FLAT PRICE @200 INR/Kg, Vendor 1, RC RAW 10 MT | D14: Contract created | E14: Completed
A15: 2 | B15: Contract Review | C15: Approve contract | D15: Contract approved | E15: Completed
A16: 3 | B16: GRN Create | C16: RC RAW 10 MT | D16: GRN created
A17: 4 | B17: Verification | C17: Dashboard, Commodity Contract Report, GRN Summary | D17: Data verified
A18: PUR-TICKET-001
A19: Step | B19: Module | C19: Action/Test Data | D19: Expected Result | E19: Autoamation Scripts
A20: 1 | B20: Purchase Contract Create | C20: RC RAW 10 MT | D20: Contract created | E20: Completed
A21: 2 | B21: Contract Review | C21: Approve contract | D21: Contract approved | E21: Completed
A22: 3 | B22: Ticketing Create | C22: Inbound GRN Ticket | D22: Ticket created
A23: 4 | B23: Ticket Review | C23: Approve Ticket | D23: Ticket approved
A24: 5 | B24: 1st Weight | C24: 15 MT | D24: Weight recorded
A25: 6 | B25: Purchase Intake | C25: 400 Units, 25 KG PP Bags, Net 10000 KG, Gross 10100 KG | D25: Intake recorded
A26: 7 | B26: 2nd Weight | C26: 4.9 MT Empty Truck | D26: Allocation and GRN auto created
A27: 8 | B27: Transaction Mapping | C27: Ticket Qty 10 MT, GRN Qty 10 MT | D27: Allocation completed
A28: 9 | B28: Verification | C28: Dashboard, Commodity Contract Report, GRN Summary | D28: Data verified

Sheet Sales-flow
A1: Sales Flow
A2: SALES-GDN-SI-001
A3: Step | B3: Module | C3: Action/Test Data | D3: Expected Result | E3: Autoamation Scripts
A4: 1 | B4: Sales Contract Create | C4: COFFEE-Sales LOCAL FLAT PRICE @200 INR/Kg, Customer 1, RC A 20 MT | D4: Contract created
A5: 2 | B5: Verification | C5: Dashboard & Commodity Contract Report | D5: Details verified
A6: 3 | B6: Contract Review | C6: Approve contract | D6: Contract approved
A7: 4 | B7: Shipping Instruction Create | C7: RC A 10 MT | D7: SI created
A8: 5 | B8: SI Review | C8: Approve SI | D8: SI approved
A9: 6 | B9: Goods Dispatch Note Create | C9: RC A 10 MT | D9: GDN created
A10: 7 | B10: Verification | C10: Dashboard, Commodity Contract Report, GDN Summary | D10: Data verified
A11: SALES-GDN-NO-SI-001
A12: Step | B12: Module | C12: Action/Test Data | D12: Expected Result | E12: Autoamation Scripts
A13: 1 | B13: Sales Contract Create | C13: COFFEE-Sales LOCAL FLAT PRICE @200 INR/Kg, Customer 1, RC A 10 MT | D13: Contract created
A14: 2 | B14: Contract Review | C14: Approve contract | D14: Contract approved
A15: 3 | B15: Goods Dispatch Note Create | C15: RC A 10 MT | D15: GDN created
A16: 4 | B16: Verification | C16: Dashboard, Commodity Contract Report, GDN Summary | D16: Data verified
A17: TICKET-SALES-001
A18: Step | B18: Module | C18: Action/Test Data | D18: Expected Result | E18: Autoamation Scripts
A19: 1 | B19: Sales Contract Create | C19: RC A 10 MT | D19: Contract created
A20: 2 | B20: Contract Review | C20: Approve contract | D20: Contract approved
A21: 3 | B21: Ticketing Create | C21: Goods Dispatch Note (Outbound) | D21: Ticket created
A22: 4 | B22: Ticketing Review | C22: Approve ticket for Customer 1 | D22: Ticket approved
A23: 5 | B23: 1st Weight Outbound | C23: 15 MT | D23: Weight recorded
A24: 6 | B24: Ticket Sales Dispatch | C24: 400 Units, 25 KG PP Bags, Net 10000 KG, Gross 10100 KG | D24: Dispatch details recorded
A25: 7 | B25: 2nd Weight | C25: 4.9 MT Empty Truck | D25: Auto allocation and GDN created
A26: 8 | B26: Reports Verification | C26: Commodity Contract Report & GDN Summary | D26: Reports verified
A27: 9 | B27: Ticket Transaction Mapping | C27: Ticket Qty 10 MT, GDN Qty 10 MT | D27: Contract allocation completed

Sheet Dependencies
A1: # | B1: Type | C1: Dependency | D1: Maven coordinates (groupId:artifactId) | E1: Version | F1: Version defined in | G1: Used for | H1: Review | I1: Note / Action
A2: 1 | B2: Language | C2: Java | D2: - | E2: 21 | F2: maven.compiler.release | G2: Language level (compiler release) | H2: OK
A3: 2 | B3: Library | C3: Selenium Java | D3: org.seleniumhq.selenium:selenium-java | E3: 4.47.0 | F3: selenium.version property | G3: Browser automation (Edge, Chrome, Firefox) | H3: OK
A4: 3 | B4: Library | C4: TestNG | D4: org.testng:testng | E4: 7.11.0 | F4: testng.version property | G4: Test runner and assertions | H4: OK
A5: 4 | B5: Library | C5: Cucumber Java | D5: io.cucumber:cucumber-java | E5: 7.34.7 | F5: cucumber.version property | G5: Gherkin step definitions | H5: OK
A6: 5 | B6: Library | C6: Cucumber TestNG | D6: io.cucumber:cucumber-testng | E6: 7.34.7 | F6: cucumber.version property | G6: Runs Cucumber features through TestNG | H6: OK | I6: Keep on the same version as cucumber-java
A7: 6 | B7: BOM | C7: Allure BOM | D7: io.qameta.allure:allure-bom | E7: 2.29.0 | F7: allure.version property | G7: Manages Allure library versions | H7: OK | I7: Imported in dependencyManagement
A8: 7 | B8: Library | C8: Allure Cucumber 7 JVM | D8: io.qameta.allure:allure-cucumber7-jvm | E8: 2.29.0 (from BOM) | F8: Allure BOM | G8: Allure reporting for Cucumber 7 | H8: OK
A9: 8 | B9: Library | C9: AspectJ Weaver | D9: org.aspectj:aspectjweaver | E9: 1.9.22 | F9: aspectj.version property | G9: Needed by Allure for @Step weaving | H9: Check | I9: No argLine -javaagent in surefire. Only needed if you use Allure @Step; otherwise the plain Cucumber plugin does not need it.
A10: 9 | B10: Library | C10: Log4j2 API | D10: org.apache.logging.log4j:log4j-api | E10: 2.25.2 | F10: log4j.version property | G10: Logging API (log.info) | H10: OK
A11: 10 | B11: Library | C11: Log4j2 Core | D11: org.apache.logging.log4j:log4j-core | E11: 2.25.2 | F11: log4j.version property | G11: Logging implementation | H11: OK
A12: 11 | B12: Library | C12: Log4j2 SLF4J2 binding | D12: org.apache.logging.log4j:log4j-slf4j2-impl | E12: 2.25.2 | F12: log4j.version property | G12: Routes Selenium SLF4J logs to Log4j2 | H12: OK | I12: Fixes the no SLF4J providers warning
A13: 12 | B13: Library | C13: Commons Configuration2 | D13: org.apache.commons:commons-configuration2 | E13: 2.11.0 | F13: Hardcoded in dependency | G13: Update values.properties | H13: OK | I13: Move version to a property for consistency
A14: 13 | B14: Library | C14: Commons Lang3 | D14: org.apache.commons:commons-lang3 | E14: 3.17.0 | F14: Hardcoded in dependency | G14: Utility classes (needed by Configuration2) | H14: Check | I14: Older release; newer versions address published security advisories. Check Maven Central.
A15: 14 | B15: Library | C15: Commons BeanUtils | D15: commons-beanutils:commons-beanutils | E15: 1.9.4 | F15: Hardcoded in dependency | G15: Needed by Configuration2 builders | H15: Check | I15: Older release; newer versions address published security advisories. Check Maven Central.
A16: 15 | B16: Library | C16: Jackson Databind | D16: com.fasterxml.jackson.core:jackson-databind | E16: 2.17.2 | F16: Hardcoded in dependency | G16: JSON test data and capturedValues.json | H16: Check | I16: Check for a newer 2.x patch release on Maven Central.
A17: 16 | B17: Plugin | C17: Cucumber for Java, Gherkin, TestNG, Allure, SonarLint, .ignore.Maven Compiler Plugin | D17: org.apache.maven.plugins:maven-compiler-plugin | E17: 3.14.1 | F17: maven.compiler.plugin.version | G17: Compiles with release 21 | H17: OK
A18: 17 | B18: Plugin | C18: Maven Surefire Plugin | D18: org.apache.maven.plugins:maven-surefire-plugin | E18: Not set (Maven default) | F18: No version in plugin block | G18: Runs tests (mvn test, pipeline) | H18: Action | I18: maven.surefire.plugin.version = 3.5.4 is defined but never used. Add <version>${maven.surefire.plugin.version}</version> to the plugin.
A19: 18 | B19: Config | C19: Surefire testFailureIgnore | D19: maven-surefire-plugin configuration | E19: true | F19: Plugin configuration | G19: Keeps the build green when tests fail | H19: Action | I19: Failing tests will not fail the Azure DevOps pipeline (CCM-013/109). Remove or set false for pipeline runs.
A20: 19 | B20: Plugin | C20: Allure Maven Plugin | D20: io.qameta.allure:allure-maven | E20: 2.12.0 | F20: allure.maven.version | G20: Generate Allure report | H20: Action | I20: installDirectory C:/tools/allure-cli is a Windows path and will fail on Linux pipeline agents. Make it a property or remove it for pipeline runs.
A21: 20 | B21: Tool | C21: Allure Report CLI | D21: reportVersion in allure-maven | E21: 2.20.1 | F21: allure-maven configuration | G21: Version of the report generator | H21: Check | I21: Differs from the Allure library version 2.29.0; consider aligning. Also confirm allure.properties sets allure.results.directory=target/allure-results, as the plugin reads that folder.
A23: Counts
A24: OK | B24: =COUNTIF($H$2:$H$21,A24) -> 12
A25: Check | B25: =COUNTIF($H$2:$H$21,A25) -> 5
A26: Action | B26: =COUNTIF($H$2:$H$21,A26) -> 3

Sheet Scenarios
A1: ID | B1: Area | C1: Module | D1: Scenario / Checklist Item | E1: Status | F1: Priority | G1: Category | H1: Execution Result | I1: Defect / Reference | J1: Notes
A2: CCM-001 | B2: Selenium framework setup | C2: Project Setup | D2: Java 21,Intellij IDE andMaven project configured | E2: Completed | F2: High | G2: Framework
A3: CCM-002 | B3: Selenium framework setup | C3: Dependencies | D3: Selenium TestNG Cucumber and Allure dependencies configured | E3: Completed | F3: High | G3: Framework
A4: CCM-003 | B4: Selenium framework setup | C4: POM | D4: LoginPage and CommodityContractManagementPage implemented | E4: Completed | F4: High | G4: Framework
A5: CCM-004 | B5: Configuration | C5: DriverFactory | D5: Browser driver initialization and configuration | E5: Completed | F5: High | G5: Framework
A6: CCM-005 | B6: Configuration | C6: Configuration | D6: URL browser username and password configuration | E6: Completed | F6: High | G6: Framework
A7: CCM-006 | B7: Reusalble utilities | C7: Utilities | D7: Reusable explicit wait utility implemented | E7: Completed | F7: High | G7: Framework
A8: CCM-007 | B8: Reusalble utilities | C8: Utilities | D8: Scroll into view utility implemented | E8: Completed | F8: Medium | G8: Framework
A9: CCM-008 | B9: Reusalble utilities | C9: Utilities | D9: JavaScript click utility implemented | E9: Completed | F9: Medium | G9: Framework
A10: CCM-009 | B10: Reusalble utilities | C10: Utilities | D10: Element highlight utility implemented | E10: Completed | F10: Medium | G10: Framework
A11: CCM-010 | B11: Reusalble utilities | C11: Allure | D11: Failure screenshot and Allure reporting implemented | E11: Completed | F11: Medium | G11: Reporting
A12: CCM-011 | B12: Hooks | C12: Hooks | D12: Scenario failure screenshot hook implemented | E12: Completed | F12: Medium | G12: Reporting
A13: CCM-012 | B13: Hooks | C13: Hooks | D13: Scenario-end logout and browser cleanup | E13: In-Progress | F13: High | G13: Teardown
... A27: CCM-026 | B27: General | C27: Contract Number | D27: Generate/capture Contract Number | E27: Completed | F27: High | G27: Functional
A28: CCM-027 | B28: General | C28: Contract Date | D28: Enter and verify Contract Date | E28: In-Progress | F28: High | G28: Defect/Validation | I28: Date format issue observed
A29: CCM-028 | B29: General | C29: Counterparty | D29: Select and verify Counterparty | E29: Completed | F29: High | G29: Functional
A30: CCM-029 | B30: General | C30: Shipper | D30: Select and verify Shipper | E30: Completed | F30: High | G30: Functional
A31: CCM-030 | B31: General | C31: References | D31: Enter and verify CP Reference 1 and CP Reference 2 | E31: Completed | F31: Medium | G31: Functional
A32: CCM-031 | B32: General | C32: Exchange | D32: Select and verify Exchange | E32: Completed | F32: Medium | G32: Functional
A33: CCM-032 | B33: General | C33: Fixation | D33: Verify Fixation By and Fixation Terms | E33: Completed | F33: Medium | G33: Functional
A34: CCM-033 | B34: General | C34: Currency | D34: Verify Invoice Currency and Price Currency/UOM | E34: Completed | F34: High | G34: Functional
A35: CCM-034 | B35: General | C35: Payment | D35: Verify Payment Terms and Payment Terms Description | E35: Completed | F35: High | G35: Functional
A36: CCM-035 | B36: General | C36: Tax | D36: Select and verify Tax Structure | E36: Completed | F36: High | G36: Functional
A37: CCM-036 | B37: General | C37: Withholding Tax | D37: Select and verify With Holding Tax Structure | E37: Completed | F37: Medium | G37: Functional
A38: CCM-037 | B38: Product Details | C38: Single Product | D38: Create one product row using JSON data | E38: Completed | F38: High | G38: Data Driven
A39: CCM-038 | B39: Product Details | C39: Multiple Products | D39: Create multiple product rows using JSON arrays | E39: Completed | F39: High | G39: Data Driven
A40: CCM-039 | B40: Product Details | C40: Product | D40: Select Product for dynamic row | E40: Completed | F40: High | G40: Functional
... A111: CCM-110 | B111: CI/CD | C111: Pipeline Reporting | D111: Publish test results and Allure artifacts from pipeline | E111: Pending | F111: Medium | G111: CI/CD

Sheet To Add
A1: ID | B1: Area | C1: Module | D1: Scenario / Checklist Item | E1: Status | F1: Priority | G1: Category | H1: Execution Result | I1: Defect / Reference | J1: Notes
A2: CCM-111 | B2: Test Data | C2: Captured Values | D2: Save captured runtime values (e.g. Contract No.) to values.properties and capturedValues.json per TestCaseId | E2: In Progress | F2: High | G2: Data Driven | J2: In progress now: TestContext + updateTheValueInJsonFile
A3: CCM-112 | B3: Test Data | C3: Captured Values Read | D3: Read the captured Contract No. back by TestCaseId in Approver and Amendment steps | E3: In Progress | F3: High | G3: Data Driven | J3: Removes hard dependency on values.properties
A4: CCM-113 | B4: Validations | C4: CCM Create | D4: Verify Price Currency/UOM is reflected in Commission Details → Value Unit when Flat Amount is selected.
A5: CCM-114 | B5: Validations | C5: CCM Create | D5: Verify all mandatory field validations are displayed when Save is clicked without entering required details.
A6: CCM-115 | B6: Test Data | C6: Schema Validation | D6: Validate JSON test data (required keys, product and commission arrays) before the browser starts | E6: Completed | F6: Medium | G6: Maintainability | J6: Extends CCM-089 from missing TestCaseId to missing fields
A7: CCM-116 | B7: Execution | C7: Retry | D7: Retry analyzer for flaky failures (max 1 retry) with retry count visible in Allure | E7: Pending | F7: Medium | G7: Execution | J7: Keep off for defect scenarios
A8: CCM-117 | B8: Execution | C8: Environment | D8: Switch URL and credentials per environment (QA/UAT) through a Maven -D property | E8: Pending | F8: High | G8: Execution | J8: Needed before the Azure DevOps pipeline (CCM-109)
A9: CCM-118 | B9: Execution | C9: Traceability | D9: Tag every Cucumber scenario with its CCM ID so results map back to this sheet | E9: Pending | F9: Medium | G9: Reporting | J9: e.g. @CCM-077
A10: CCM-119 | B10: Execution | C10: A | D10: Run Smoke suite on Chrome and Edge | E10: Completed | F10: Low | G10: Execution
A11: CCM-120 | B11: Reporting | C11: Allure History | D11: Keep Allure history and trends between pipeline runs | E11: Pending | F11: Low | G11: Reporting | J11: Link to CCM-110
A12: CCM-121 | B12: Workflow | C12: Reject | D12: Approver rejects a contract; verify rejection message and Rejected status | E12: Pending | F12: High | G12: E2E | J12: Confirm with app: reject flow exists
A13: CCM-122 | B13: Workflow | C13: Modify/Edit Pending | D13: Edit a Pending contract before approval and verify changes are saved | E13: Pending | F13: Medium | G13: Workflow | J13: Confirm with app
A14: CCM-123 | B14: Workflow | C14: Cancel Create | D14: Cancel the Create Contract screen and verify nothing is saved | E14: Pending | F14: Medium | G14: Negative
A15: CCM-124 | B15: Workflow | C15: View Approved | D15: Verify an Approved contract opens read-only (fields disabled) | E15: Pending | F15: Medium | G15: Validation
A16: CCM-125 | B16: Workflow | C16: Amendment History | D16: Verify status and history of original vs amended contract after Amendment approval | E16: Pending | F16: Medium | G16: Workflow | J16: Extends CCM-084
A17: CCM-126 | B17: Contract List | C17: Search By Contract No | D17: Search the list by captured Contract No. and verify the correct row is returned | E17: Completed | F17: High | G17: Functional | J17: Your capture step already reads the list column
A18: CCM-127 | B18: Contract List | C18: Filters | D18: Filter list by Status, Counterparty and Date range | E18: Pending | F18: Medium | G18: Functional
A19: CCM-128 | B19: Contract List | C19: Grid Behaviour | D19: Verify pagination, sorting and column visibility on the list | E19: Pending | F19: Low | G19: Functional
A20: CCM-129 | B20: Calculations | C20: Product Totals | D20: Verify product row total and contract total (Quantity x Price) | E20: Pending | F20: High | G20: Validation | J20: Confirm formula with BA
A21: CCM-130 | B21: Calculations | C21: Commission Amount | D21: Verify commission amount for Percentage, Flat and Value types | E21: Pending | F21: High | G21: Validation | J21: CCM-064 covers input combinations, not the calculated result
A22: CCM-131 | B22: Calculations | C22: Tax Amounts | D22: Verify Tax and Withholding Tax amounts for the selected structures | E22: Pending | F22: Medium | G22: Validation | J22: Confirm formula with BA
A23: CCM-132 | B23: Product Details | C23: Delete Row | D23: Delete a product row and verify remaining rows and totals | E23: Pending | F23: Medium | G23: Dynamic UI
A24: CCM-133 | B24: Product Details | C24: Many Rows | D24: Add 10+ product rows and verify row-relative locators still hold | E24: Pending | F24: Low | G24: Dynamic UI | J24: Link to CCM-093
A25: CCM-134 | B25: Product Details | C25: Date Rules | D25: Target Date From not after To; Trade Month / Position Month consistency | E25: Pending | F25: Medium | G25: Negative | J25: Confirm rules with BA
A26: CCM-135 | B26: Commission | C26: Delete Row | D26: Delete a commission row and verify remaining rows | E26: Pending | F26: Medium | G26: Dynamic UI
A27: CCM-136 | B27: General | C27: Dependent Dropdowns | D27: Verify Billing, Shipping and Shipper options depend on the selected Counterparty | E27: Pending | F27: Medium | G27: Functional | J27: Confirm with app
A28: CCM-137 | B28: General | C28: Contract Date Retest | D28: Retest Contract Date after the date-format defect is fixed | E28: Pending | F28: High | G28: Defect/Validation | J28: Link to CCM-027
A29: CCM-138 | B29: Login | C29: Session | D29: Verify logout and session-timeout behaviour | E29: Pending | F29: Low | G29: Security
